<?xml version="1.0"?>
<EntityTemplate>
    <Components>
		<Metadata>
			<Name>Turret</Name>
		</Metadata>
		<Timer>
		</Timer>
		<Fsm>
			<States>
				<State FsmName="Turret.Rotation" StateName="Idle" />
			</States>
		</Fsm>
		<Animation>
			<States>
				<State>
					<Speed>10</Speed>
					<Loop>true</Loop>
				</State>
			</States>
		</Animation>
		<Position X="$(startX)" Y="$(startY)" />
		<Thrust X="0" Y="0" />
		<Velocity X="0" Y="0" />
		<AngularPosition>
			<Value>0</Value>
		</AngularPosition>
		<Body>
			<CofFactor>1.0</CofFactor>
			<CorFactor>0.0</CorFactor>
			<Fixtures>
				<Fixture>
					<ShapeName>Shapes/Box_0_0_32_32</ShapeName>
					<Groups>
						<Group>Solid</Group>
					</Groups>
				</Fixture>
			</Fixtures>
		</Body>
		<Motion></Motion>
		<Sprite>
			<AtlasName>Atlases/Sprites/Turret</AtlasName>
			<ImageIndex>0</ImageIndex>
			<Origin X="0" Y="0" />
			<Order>100</Order>
		</Sprite>
		<Text>
			<Text>Turret</Text>
			<Offset X="0" Y="32" />
			<Color R="255" G="255" B="255" A="255" />
			<FontName>Arial</FontName>
			<FontSize>9</FontSize>
			<Order>0</Order>
		</Text>
    </Components>
</EntityTemplate>